[
  {
    "id": "user_intro",
    "title": "User Guide Introduction",
    "url": "/biodynamo/doc/user_guide/docs/",
    "tags": ["intro", "user"],
    "image": null,
    "date": "2016-12-07T00:00:00Z"
  },
  {
    "id": "install",
    "title": "Installation",
    "url": "/biodynamo/doc/user_guide/docs/installation/",
    "tags": ["install", "setup"],
    "image": null,
    "date": "2016-12-07T00:00:00Z"
  },
  {
    "id": "tutorials",
    "title": "Tutorials",
    "url": "/biodynamo/doc/user_guide/docs/hello_world/",
    "tags": ["tutorial", "setup"],
    "image": null,
    "date": "2016-12-07T00:00:00Z"
  },
  {
    "id": "viz",
    "title": "Visualization",
    "url": "/biodynamo/doc/user_guide/docs/visualization/",
    "tags": ["setup", "visualization"],
    "image": null,
    "date": "2016-12-07T00:00:00Z"
  },
  {
    "id": "diffuse",
    "title": "Diffusion",
    "url": "/biodynamo/doc/user_guide/docs/diffusion/",
    "tags": ["diffusion", "setup"],
    "image": null,
    "date": "2016-12-07T00:00:00Z"
  },
  {
    "id": "tumor_concept",
    "title": "Tumor Concept",
    "url": "/biodynamo/doc/user_guide/docs/tumor_concept/",
    "tags": ["tumor", "setup","theory"],
    "image": null,
    "date": "2016-12-07T00:00:00Z"
  },
  {
    "id": "parameter",
    "title": "Parameter",
    "url": "/biodynamo/doc/user_guide/docs/parameter/",
    "tags": ["documentation", "parameter"],
    "image": null,
    "date": "2016-12-07T00:00:00Z"
  },
  {
    "id": "event",
    "title": "Event",
    "url": "/biodynamo/doc/user_guide/docs/event/",
    "tags": ["event", "documentation"],
    "image": null,
    "date": "2016-12-07T00:00:00Z"
  },
  {
    "id": "math_array",
    "title": "Math Array",
    "url": "/biodynamo/doc/user_guide/docs/math_array/",
    "tags": ["math", "documentation"],
    "image": null,
    "date": "2016-12-07T00:00:00Z"
  },
  {
    "id": "operation",
    "title": "Operation",
    "url": "/biodynamo/doc/user_guide/docs/operation/",
    "tags": ["operation", "documentation"],
    "image": null,
    "date": "2016-12-07T00:00:00Z"
  },
  {
    "id": "substance",
    "title": "Substance Initialization",
    "url": "/biodynamo/doc/user_guide/docs/substance_initializers/",
    "tags": ["substance", "initialize","documentation"],
    "image": null,
    "date": "2016-12-07T00:00:00Z"
  },
  {
    "id": "gpu",
    "title": "GPU Acceleration",
    "url": "/biodynamo/doc/user_guide/docs/gpu_acceleration/",
    "tags": ["gpu", "documentation","acceleration", "speed"],
    "image": null,
    "date": "2016-12-07T00:00:00Z"
  },
  {
    "id": "opengl",
    "title": "OpenGL Issues",
    "url": "/biodynamo/doc/user_guide/docs/opengl_issues/",
    "tags": ["trouble", "opengl", "difficulties"],
    "image": null,
    "date": "2016-12-07T00:00:00Z"
  },
  {
    "id": "log",
    "title": "ChangeLog",
    "url": "/biodynamo/doc/user_guide/docs/changelog/",
    "tags": ["change", "documentation","log"],
    "image": null,
    "date": "2016-12-07T00:00:00Z"
  },
  {
    "id": "contact",
    "title": "Contact",
    "url": "/biodynamo/doc/user_guide/docs/contact/",
    "tags": ["contact", "documentation"],
    "image": null,
    "date": "2016-12-07T00:00:00Z"
  },
  {
    "id": "dev_intro",
    "title": "Dev Guide Introduction",
    "url": "/biodynamo/doc/dev_guide/docs/",
    "tags": ["developer", "guide"],
    "image": null,
    "date": "2016-12-07T00:00:00Z"
  },
  {
    "id": "build_bio",
    "title": "Build BioDynaMo",
    "url": "/biodynamo/doc/dev_guide/docs/build",
    "tags": ["build", "documentation","developer"],
    "image": null,
    "date": "2016-12-07T00:00:00Z"
  },
  {
    "id": "code_quality",
    "title": "Code Quality",
    "url": "/biodynamo/doc/dev_guide/docs/code_quality",
    "tags": ["code", "quality", "developer", "documentation"],
    "image": null,
    "date": "2016-12-07T00:00:00Z"
  },
  {
    "id": "contribute",
    "title": "COntribute",
    "url": "/biodynamo/doc/dev_guide/docs/contribute",
    "tags": ["contribution", "developer", "help", "documentation"],
    "image": null,
    "date": "2016-12-07T00:00:00Z"
  },
 
]